promptware/__init__.py
promptware/config.py
promptware/dataset.py
promptware/info.py
promptware/licenses.py
promptware/load.py
promptware/load_test.py
promptware/module_test.py
promptware/promptware.py
promptware/software.py
promptware/tasks.py
promptware/artifacts/__init__.py
promptware/artifacts/utils.py
promptware/artifacts/test_modules/__init__.py
promptware/artifacts/test_modules/boo_prompt.py
promptware/artifacts/test_modules/foo_prompt.py
promptware/artifacts/test_modules/xyz.py
promptware/artifacts/test_modules/xyz2.py
promptware/constants/__init__.py
promptware/constants/applications.py
promptware/constants/design_patterns.py
promptware/constants/languages.py
promptware/constants/licenses.py
promptware/constants/platforms.py
promptware/constants/tasks.py
promptware/kernels/__init__.py
promptware/kernels/kernel.py
promptware/kernels/plm.py
promptware/kernels/python.py
promptware/kernels/api/__init__.py
promptware/kernels/api/huggingface.py
promptware/kernels/api/huggingface_test.py
promptware/tests/__init__.py
promptware/tests/custom_software_test.py
promptware/tests/python_test.py
promptware/tests/scoring_test.py
promptware/utils/__init__.py
promptware/utils/datalab_util.py
promptware/utils/download.py
promptware/utils/eval_util.py
promptware/utils/extract.py
promptware/utils/extract_test.py
promptware/utils/file_utils.py
promptware/utils/file_utils_test.py
promptware/utils/filelock.py
promptware/utils/logging.py
promptware/utils/logprobs_utils.py
promptware/utils/logprobs_utils_test.py
promptware/utils/naming.py
promptware/utils/prompt_utils.py
promptware/utils/py_util.py
promptware/utils/py_util_test.py
promptware/utils/software_util.py
promptware/utils/version.py
softwares/__init__.py
softwares/ad_from_product_description/__init__.py
softwares/ad_from_product_description/software.py
softwares/ad_from_product_description/software_test.py
softwares/analogy_maker/__init__.py
softwares/analogy_maker/software.py
softwares/analogy_maker/software_test.py
promptware-0.1.3.dev0.dist-info/LICENSE
promptware-0.1.3.dev0.dist-info/METADATA
promptware-0.1.3.dev0.dist-info/WHEEL
promptware-0.1.3.dev0.dist-info/top_level.txt
promptware-0.1.3.dev0.dist-info/RECORD
