Metadata-Version: 2.1
Name: promptware
Version: 0.1.3.dev0
Summary: Software 3.0
Home-page: https://github.com/ExpressAI/Promptware
Author: Express AI
License: Apache License
Platform: UNKNOWN
Classifier: Intended Audience :: Developers
Classifier: Topic :: Text Processing
Classifier: Topic :: Scientific/Engineering :: Artificial Intelligence
Classifier: License :: OSI Approved :: Apache Software License
Classifier: Programming Language :: Python :: 3.9
Classifier: Programming Language :: Python :: 3.10
Classifier: Programming Language :: Python :: 3 :: Only
License-File: LICENSE
Requires-Dist: nltk (>=3.2)
Requires-Dist: numpy
Requires-Dist: scipy
Requires-Dist: matplotlib
Requires-Dist: scikit-learn
Requires-Dist: pre-commit
Requires-Dist: tqdm
Requires-Dist: openai
Requires-Dist: datalabs
Requires-Dist: cohere
Requires-Dist: python-dotenv
Requires-Dist: transformers
Requires-Dist: torch
